{
  "run": {
    "command": "nx build @go-ui/vue",
    "startTime": "2025-10-25T07:10:40.263Z",
    "endTime": "2025-10-25T07:11:30.084Z",
    "inner": false
  },
  "tasks": [
    {
      "taskId": "@go-ui/core:build",
      "target": "build",
      "projectName": "@go-ui/core",
      "hash": "1700303419346037433",
      "startTime": "2025-10-25T07:10:40.288Z",
      "endTime": "2025-10-25T07:11:11.591Z",
      "params": "",
      "cacheStatus": "cache-miss",
      "status": 0
    },
    {
      "taskId": "@go-ui/vue:build",
      "target": "build",
      "projectName": "@go-ui/vue",
      "hash": "17483199442932183474",
      "startTime": "2025-10-25T07:11:11.594Z",
      "endTime": "2025-10-25T07:11:30.083Z",
      "params": "",
      "cacheStatus": "cache-miss",
      "status": 0
    }
  ]
}